json2gro/__init__.py
json2gro/gro_file_compiler.py
json2gro/params.py
json2gro/ui_parameters.py
json2gro-0.0b3.dist-info/METADATA
json2gro-0.0b3.dist-info/WHEEL
json2gro-0.0b3.dist-info/top_level.txt
json2gro-0.0b3.dist-info/RECORD
