Metadata-Version: 2.4
Name: json2gro
Version: 0.0b3
Summary: This package converts json to gro
Author-email: Catalina Lorca <catalina.lorca_b@mail.udp.cl>, Fernanda Lorca <fernanda.lorca_b@mail.udp.cl>
Maintainer-email: Catalina Lorca <catalina.lorca_b@mail.udp.cl>, Fernanda Lorca <fernanda.lorca_b@mail.udp.cl>
License-Expression: MIT
Project-URL: Homepage, https://github.com/frnvnd4/json2gro/
Project-URL: Bug Tracker, https://github.com/frnvnd4/json2gro/issues
Keywords: SBOL,GRO,converter,JSON,synthetic biology
Classifier: Programming Language :: Python :: 3
Classifier: Operating System :: OS Independent
Requires-Python: >=3.7
Requires-Dist: sbol3
Requires-Dist: xmltodict
Requires-Dist: lxml
Requires-Dist: jsonschema
Requires-Dist: pandas
Requires-Dist: matplotlib
Requires-Dist: seaborn
Requires-Dist: ipywidgets
Provides-Extra: test
Requires-Dist: pytest<5.0.0; extra == "test"
Requires-Dist: pytest-cov[all]; extra == "test"
